pptestszymonradosz/__init__.py
pptestszymonradosz/m_mod_pptest.py
pptestszymonradosz-0.0.4.dist-info/LICENSE.txt
pptestszymonradosz-0.0.4.dist-info/METADATA
pptestszymonradosz-0.0.4.dist-info/WHEEL
pptestszymonradosz-0.0.4.dist-info/top_level.txt
pptestszymonradosz-0.0.4.dist-info/RECORD
