Metadata-Version: 2.1
Name: pptestszymonradosz
Version: 0.0.4
Summary: My test package
Author-email: SzR <algobitpl@gmail.com>
License: MIT License
Keywords: pptestszymonradosz,funny functions,name,surname,personal data
Classifier: Framework :: IDLE
Classifier: License :: Free For Educational Use
Requires-Python: >=3.0
License-File: LICENSE.txt
Requires-Dist: numpy ; python_version >= "3.0"
